clatmenow/__init__.py
clatmenow/clatmenow.py
clatmenow/cli.py
clatmenow/regions.py
clatmenow-0.1.1.dist-info/AUTHORS.rst
clatmenow-0.1.1.dist-info/LICENSE
clatmenow-0.1.1.dist-info/METADATA
clatmenow-0.1.1.dist-info/WHEEL
clatmenow-0.1.1.dist-info/entry_points.txt
clatmenow-0.1.1.dist-info/top_level.txt
clatmenow-0.1.1.dist-info/RECORD
